{
  "coverage": "18.75%",
  "expectCount": 48,
  "actualCount": 9,
  "files": {
    "lib/cypher.js": {
      "expectCount": 7,
      "actualCount": 0,
      "undocumentLines": [
        6,
        21,
        7,
        75,
        22,
        38,
        20
      ]
    },
    "lib/model.js": {
      "expectCount": 2,
      "actualCount": 0,
      "undocumentLines": [
        5,
        83
      ]
    },
    "lib/node.js": {
      "expectCount": 9,
      "actualCount": 1,
      "undocumentLines": [
        16,
        10,
        15,
        14,
        13,
        17,
        18,
        62
      ]
    },
    "lib/errors.js": {
      "expectCount": 6,
      "actualCount": 4,
      "undocumentLines": [
        40,
        16
      ]
    },
    "lib/schema.js": {
      "expectCount": 6,
      "actualCount": 4,
      "undocumentLines": [
        37,
        38
      ]
    },
    "lib/relations/belongsToOne.js": {
      "expectCount": 8,
      "actualCount": 0,
      "undocumentLines": [
        6,
        3,
        4,
        10,
        8,
        11,
        9,
        7
      ]
    },
    "lib/relations/index.js": {
      "expectCount": 2,
      "actualCount": 0,
      "undocumentLines": [
        8,
        4
      ]
    },
    "lib/relations/hasMany.js": {
      "expectCount": 8,
      "actualCount": 0,
      "undocumentLines": [
        4,
        3,
        10,
        8,
        6,
        11,
        9,
        7
      ]
    }
  }
}